{"cameraMode":{"drawMode":0,"name":"Shaded","section":"Shading Mode"},"sceneLighting":true,"audioPlay":false,"sceneViewState":{"m_AlwaysRefresh":false,"showFog":true,"showSkybox":true,"showFlares":true,"showImageEffects":true,"showParticleSystems":true,"showVisualEffectGraphs":true,"m_FxEnabled":true},"in2DMode":false,"pivot":{"x":-1.669384241104126,"y":-4.2884368896484379,"z":90.0940170288086},"rotation":{"x":-0.06028178706765175,"y":0.014289298094809056,"z":-0.0007088189595378935,"w":-0.998302698135376},"size":59.39572525024414,"orthographic":false}